Metadata-Version: 2.1
Name: frheed
Version: 0.0.2
Summary: FRHEED is a GUI for real-time Reflection High-Energy Electron Diffraction (RHEED) analysis.
Home-page: https://github.com/ecyoung3/FRHEED
Author: Elliot Young
Author-email: elliot.young1996@gmail.com
License: UNKNOWN
Platform: UNKNOWN
Classifier: Programming Language :: Python :: 3.8
License-File: LICENSE
Requires-Dist: setuptools
Requires-Dist: PyQt5
Requires-Dist: spyder
Requires-Dist: Pillow
Requires-Dist: appdirs
Requires-Dist: IPython
Requires-Dist: scipy (==1.5.4)
Requires-Dist: matplotlib (==3.3.3)
Requires-Dist: cmapy (==0.6.6)
Requires-Dist: pyqtgraph (==0.11.0)
Requires-Dist: opencv-python (==3.4.14.51)
